src/__init__.py
src/agent.py
src/dotenv.py
src/fastapi_example.py
src/main.py
src/models.py
src/schemas.py
src/utils.py
fastai_agent-0.1.3.dist-info/METADATA
fastai_agent-0.1.3.dist-info/WHEEL
fastai_agent-0.1.3.dist-info/licenses/LICENSE
fastai_agent-0.1.3.dist-info/RECORD
