Metadata-Version: 2.4
Name: fastai-agent
Version: 0.1.3
Summary: Fastai Agent - 一个基于 FastAPI 和 LangGraph 的智能代理框架
Project-URL: Homepage, https://github.com/yourusername/fastai-agent
Project-URL: Documentation, https://fastai-agent.readthedocs.io/
Project-URL: Repository, https://github.com/yourusername/fastai-agent.git
Project-URL: Issues, https://github.com/yourusername/fastai-agent/issues
Author-email: jackjack <your.email@example.com>
License: MIT
License-File: LICENSE
Classifier: Development Status :: 3 - Alpha
Classifier: Intended Audience :: Developers
Classifier: License :: OSI Approved :: MIT License
Classifier: Programming Language :: Python :: 3
Classifier: Programming Language :: Python :: 3.12
Classifier: Topic :: Software Development :: Libraries :: Python Modules
Requires-Python: >=3.12
Requires-Dist: fastapi>=0.115.12
Requires-Dist: langchain-openai>=0.3.19
Requires-Dist: langchain>=0.3.25
Requires-Dist: langgraph>=0.4.7
Requires-Dist: pydantic>=2.11.5
Requires-Dist: python-dotenv>=1.1.0
Requires-Dist: tortoise-orm>=0.25.1
Requires-Dist: uvicorn>=0.34.3
